iglu_r/__init__.py
iglu_r/bridge.py
iglu_r/df.py
iglu_r/iglu_3.5.0.tar.gz
iglu_r/metrics.py
iglu_r/data/example_data_1_subject.csv
iglu_r/data/example_data_5_subject.csv
iglu_r/data/example_data_hall.csv
iglu_r/data/example_meals_hall.csv
iglu_r-0.0.9.dist-info/METADATA
iglu_r-0.0.9.dist-info/WHEEL
iglu_r-0.0.9.dist-info/top_level.txt
iglu_r-0.0.9.dist-info/RECORD
